Dsend/__init__.py
Dsend/dsend.py
Dsend-0.6.dist-info/METADATA
Dsend-0.6.dist-info/WHEEL
Dsend-0.6.dist-info/top_level.txt
Dsend-0.6.dist-info/RECORD
